MANIFEST.in
requirements.txt
setup.py
fetchr/__init__.py
fetchr/__init__.pyc
fetchr/fetchr.py
fetchr/fetchr.pyc
fetchr.egg-info/PKG-INFO
fetchr.egg-info/SOURCES.txt
fetchr.egg-info/dependency_links.txt
fetchr.egg-info/entry_points.txt
fetchr.egg-info/requires.txt
fetchr.egg-info/top_level.txt
fetchr/data/config.yaml