Metadata-Version: 1.0
Name: fetchr
Version: 0.0.2
Summary: A tool to load files from the internet
Home-page: UNKNOWN
Author: George Erickson
Author-email: george55@mit.edu
License: UNKNOWN
Download-URL: https://github.com/GeorgeErickson/fetchr/zipball/v0.0.2
Platform: UNKNOWN
